meca/common/config/__init__.py
meca/common/config/models.py
meca_common_config-1.0.4.dist-info/METADATA
meca_common_config-1.0.4.dist-info/WHEEL
meca_common_config-1.0.4.dist-info/top_level.txt
meca_common_config-1.0.4.dist-info/RECORD
