Metadata-Version: 2.4
Name: meca-common-config
Version: 1.0.4
Summary: 配置工具类
Author: jgdqdlr
Requires-Python: >=3.10
